oxrpy/__init__.py
oxrpy/oxrpy.py
oxrpy-1.3.4.dist-info/licenses/LICENSE
oxrpy-1.3.4.dist-info/METADATA
oxrpy-1.3.4.dist-info/WHEEL
oxrpy-1.3.4.dist-info/top_level.txt
oxrpy-1.3.4.dist-info/RECORD
