Metadata-Version: 2.4
Name: oxrpy
Version: 1.3.4
Summary: Python wrapper for the Oxford Response API
Project-URL: Homepage, https://github.com/BLK-TTAUDI/OXRPY
Project-URL: Repository, https://github.com/BLK-TTAUDI/OXRPY
Classifier: Programming Language :: Python :: 3
Classifier: License :: Other/Proprietary License
Classifier: Operating System :: OS Independent
Requires-Python: >=3.6
License-File: LICENSE
Requires-Dist: requests
Dynamic: license-file
